{"mean":{"confidence_interval":{"confidence_level":0.95,"lower_bound":8146471.301428572,"upper_bound":8180663.804357142},"point_estimate":8162848.389999999,"standard_error":8740.546464655721},"median":{"confidence_interval":{"confidence_level":0.95,"lower_bound":8122024.285714285,"upper_bound":8152106.571428572},"point_estimate":8138283.714285715,"standard_error":8197.706892333863},"median_abs_dev":{"confidence_interval":{"confidence_level":0.95,"lower_bound":37382.59343632669,"upper_bound":70506.73614825502},"point_estimate":51980.37867716341,"standard_error":7969.743701130917},"slope":null,"std_dev":{"confidence_interval":{"confidence_level":0.95,"lower_bound":63896.58152962052,"upper_bound":110716.68050542062},"point_estimate":88040.8693320488,"standard_error":12064.533446874264}}