{"mean":{"confidence_interval":{"confidence_level":0.95,"lower_bound":44704101.591875,"upper_bound":44819418.05125},"point_estimate":44759854.355,"standard_error":29323.004618338986},"median":{"confidence_interval":{"confidence_level":0.95,"lower_bound":44671232.0,"upper_bound":44787846.0},"point_estimate":44713754.0,"standard_error":30423.050273366505},"median_abs_dev":{"confidence_interval":{"confidence_level":0.95,"lower_bound":149527.62034535408,"upper_bound":232319.33872550726},"point_estimate":190424.0286692977,"standard_error":21708.095624242236},"slope":null,"std_dev":{"confidence_interval":{"confidence_level":0.95,"lower_bound":215964.61899754766,"upper_bound":365535.3120340037},"point_estimate":293500.50044299645,"standard_error":38249.358222912604}}