{"mean":{"confidence_interval":{"confidence_level":0.95,"lower_bound":47724774.495,"upper_bound":47857840.682375},"point_estimate":47790585.015,"standard_error":33846.444740606836},"median":{"confidence_interval":{"confidence_level":0.95,"lower_bound":47681575.0,"upper_bound":47928517.0},"point_estimate":47786969.75,"standard_error":64503.31014867053},"median_abs_dev":{"confidence_interval":{"confidence_level":0.95,"lower_bound":317601.45441144705,"upper_bound":489904.4049024582},"point_estimate":435494.09781843424,"standard_error":42937.8956041724},"slope":null,"std_dev":{"confidence_interval":{"confidence_level":0.95,"lower_bound":302812.34115142655,"upper_bound":375073.80692441715},"point_estimate":341336.48098329286,"standard_error":18416.3246639623}}