{"mean":{"confidence_interval":{"confidence_level":0.95,"lower_bound":9352.093829748697,"upper_bound":9399.55490351954},"point_estimate":9375.888052839906,"standard_error":12.087827196568938},"median":{"confidence_interval":{"confidence_level":0.95,"lower_bound":9320.722701149425,"upper_bound":9434.541273584906},"point_estimate":9381.308058261184,"standard_error":30.793557340007013},"median_abs_dev":{"confidence_interval":{"confidence_level":0.95,"lower_bound":112.79835836401534,"upper_bound":167.80161512765045},"point_estimate":148.76764624416612,"standard_error":13.532485674758412},"slope":{"confidence_interval":{"confidence_level":0.95,"lower_bound":9313.14915366118,"upper_bound":9353.894065206527},"point_estimate":9331.683216713462,"standard_error":10.427916209104414},"std_dev":{"confidence_interval":{"confidence_level":0.95,"lower_bound":105.64720981073451,"upper_bound":137.88595852812378},"point_estimate":121.56804140695891,"standard_error":8.26721858742713}}