{"mean":{"confidence_interval":{"confidence_level":0.95,"lower_bound":6485.955571155037,"upper_bound":6521.94032744203},"point_estimate":6502.751515743247,"standard_error":9.19960848194597},"median":{"confidence_interval":{"confidence_level":0.95,"lower_bound":6476.220207570208,"upper_bound":6494.969520565357},"point_estimate":6486.44088136927,"standard_error":4.717235579260822},"median_abs_dev":{"confidence_interval":{"confidence_level":0.95,"lower_bound":34.565933920343035,"upper_bound":57.06325125965291},"point_estimate":46.96963622107788,"standard_error":5.970622286800921},"slope":{"confidence_interval":{"confidence_level":0.95,"lower_bound":6486.028949443855,"upper_bound":6508.346021442476},"point_estimate":6496.378214638915,"standard_error":5.712023676023597},"std_dev":{"confidence_interval":{"confidence_level":0.95,"lower_bound":60.203992990462346,"upper_bound":121.02987536479014},"point_estimate":92.78813066391437,"standard_error":15.54586693770658}}