{"mean":{"confidence_interval":{"confidence_level":0.95,"lower_bound":7227622.228357142,"upper_bound":7344382.412857138},"point_estimate":7284103.89571429,"standard_error":29779.248973147573},"median":{"confidence_interval":{"confidence_level":0.95,"lower_bound":7164362.428571429,"upper_bound":7280999.0},"point_estimate":7211898.571428571,"standard_error":32210.40386505229},"median_abs_dev":{"confidence_interval":{"confidence_level":0.95,"lower_bound":183395.07514408755,"upper_bound":307059.6920486002},"point_estimate":235652.06461633934,"standard_error":30631.13618397833},"slope":null,"std_dev":{"confidence_interval":{"confidence_level":0.95,"lower_bound":246445.5390852395,"upper_bound":344607.6705369936},"point_estimate":297828.2982567028,"standard_error":25117.16872043508}}