{"mean":{"confidence_interval":{"confidence_level":0.95,"lower_bound":7995573.540178573,"upper_bound":8049907.141178572},"point_estimate":8022406.81714286,"standard_error":13868.542563544592},"median":{"confidence_interval":{"confidence_level":0.95,"lower_bound":7980293.571428571,"upper_bound":8071542.142857143},"point_estimate":8029642.0,"standard_error":25441.783861193893},"median_abs_dev":{"confidence_interval":{"confidence_level":0.95,"lower_bound":116072.96373929277,"upper_bound":188537.57905278838},"point_estimate":155109.39744625724,"standard_error":19149.64894065802},"slope":null,"std_dev":{"confidence_interval":{"confidence_level":0.95,"lower_bound":116261.54913413854,"upper_bound":167624.24401569593},"point_estimate":140342.13563214804,"standard_error":13585.353966573863}}