{"mean":{"confidence_interval":{"confidence_level":0.95,"lower_bound":44374849.213250004,"upper_bound":44597911.41},"point_estimate":44461827.9,"standard_error":59859.62191320409},"median":{"confidence_interval":{"confidence_level":0.95,"lower_bound":44453675.5,"upper_bound":44486626.75},"point_estimate":44471972.0,"standard_error":7741.752559740759},"median_abs_dev":{"confidence_interval":{"confidence_level":0.95,"lower_bound":51219.38129067421,"upper_bound":119557.97382742167},"point_estimate":85695.01977860928,"standard_error":19038.26743683034},"slope":null,"std_dev":{"confidence_interval":{"confidence_level":0.95,"lower_bound":169394.17056170374,"upper_bound":1005746.2503847202},"point_estimate":604326.7641397876,"standard_error":284473.11808693537}}