{"mean":{"confidence_interval":{"confidence_level":0.95,"lower_bound":8309.641494741754,"upper_bound":8401.510264529265},"point_estimate":8350.177237028207,"standard_error":23.581438793257778},"median":{"confidence_interval":{"confidence_level":0.95,"lower_bound":8280.574668778801,"upper_bound":8391.168831699346},"point_estimate":8368.485279922781,"standard_error":33.41087722955658},"median_abs_dev":{"confidence_interval":{"confidence_level":0.95,"lower_bound":99.807620634991,"upper_bound":160.30351476768115},"point_estimate":138.15294457738224,"standard_error":14.554710814859762},"slope":{"confidence_interval":{"confidence_level":0.95,"lower_bound":8286.65721283587,"upper_bound":8382.387078787575},"point_estimate":8326.221258866559,"standard_error":24.82649594560678},"std_dev":{"confidence_interval":{"confidence_level":0.95,"lower_bound":119.88833222716025,"upper_bound":361.3063904008957},"point_estimate":237.20608132997586,"standard_error":72.70834112989354}}