{"mean":{"confidence_interval":{"confidence_level":0.95,"lower_bound":9291.0634283795,"upper_bound":9354.464046821096},"point_estimate":9321.954082140308,"standard_error":16.184047345403563},"median":{"confidence_interval":{"confidence_level":0.95,"lower_bound":9249.09375,"upper_bound":9351.857236842105},"point_estimate":9316.535305059522,"standard_error":26.91943496693865},"median_abs_dev":{"confidence_interval":{"confidence_level":0.95,"lower_bound":121.50319062146777,"upper_bound":187.5725678938791},"point_estimate":162.39920252308522,"standard_error":16.964450191459136},"slope":{"confidence_interval":{"confidence_level":0.95,"lower_bound":9239.731862921448,"upper_bound":9334.203247584677},"point_estimate":9281.947673452047,"standard_error":24.295481001016693},"std_dev":{"confidence_interval":{"confidence_level":0.95,"lower_bound":124.67207367194926,"upper_bound":199.29161858779247},"point_estimate":162.53672823848916,"standard_error":19.14800805968294}}