{"mean":{"confidence_interval":{"confidence_level":0.95,"lower_bound":9021.319631459171,"upper_bound":9069.460872617874},"point_estimate":9045.36788868829,"standard_error":12.260376306507432},"median":{"confidence_interval":{"confidence_level":0.95,"lower_bound":8982.512152777777,"upper_bound":9096.32704326923},"point_estimate":9038.208059210527,"standard_error":28.76982866991767},"median_abs_dev":{"confidence_interval":{"confidence_level":0.95,"lower_bound":100.43332621761449,"upper_bound":174.06418295892604},"point_estimate":146.41759286109493,"standard_error":18.00576732625785},"slope":{"confidence_interval":{"confidence_level":0.95,"lower_bound":8979.987964713644,"upper_bound":9019.234080521148},"point_estimate":8997.96963757943,"standard_error":10.021766215902383},"std_dev":{"confidence_interval":{"confidence_level":0.95,"lower_bound":108.68097192274809,"upper_bound":136.08216128052186},"point_estimate":123.03921288769781,"standard_error":6.9857494331471655}}