{"mean":{"confidence_interval":{"confidence_level":0.95,"lower_bound":9707.422087578014,"upper_bound":9791.174543916788},"point_estimate":9747.3962954935,"standard_error":21.386975695969976},"median":{"confidence_interval":{"confidence_level":0.95,"lower_bound":9649.537254901961,"upper_bound":9715.426987670067},"point_estimate":9674.432543209878,"standard_error":16.47905120091584},"median_abs_dev":{"confidence_interval":{"confidence_level":0.95,"lower_bound":89.5994864409405,"upper_bound":175.09420331196975},"point_estimate":123.5624696684384,"standard_error":21.447539592270427},"slope":{"confidence_interval":{"confidence_level":0.95,"lower_bound":9634.236610862868,"upper_bound":9705.300663062375},"point_estimate":9663.848707551351,"standard_error":18.363650603550866},"std_dev":{"confidence_interval":{"confidence_level":0.95,"lower_bound":157.9856532165401,"upper_bound":268.9887871626605},"point_estimate":215.6503067772908,"standard_error":28.47129618624738}}