{"mean":{"confidence_interval":{"confidence_level":0.95,"lower_bound":9029.19315701309,"upper_bound":9116.72947464392},"point_estimate":9071.823767766296,"standard_error":22.35594600101228},"median":{"confidence_interval":{"confidence_level":0.95,"lower_bound":8965.215811965812,"upper_bound":9142.567765567766},"point_estimate":9109.411123795453,"standard_error":50.15233585401604},"median_abs_dev":{"confidence_interval":{"confidence_level":0.95,"lower_bound":195.07370312684947,"upper_bound":283.83517629995174},"point_estimate":250.62310618431272,"standard_error":22.503226892184582},"slope":{"confidence_interval":{"confidence_level":0.95,"lower_bound":9013.74291663959,"upper_bound":9084.280156920431},"point_estimate":9051.216317877483,"standard_error":17.990847080119497},"std_dev":{"confidence_interval":{"confidence_level":0.95,"lower_bound":183.4012094951878,"upper_bound":270.58214864826584},"point_estimate":225.0430222656631,"standard_error":22.713321717963844}}