{"mean":{"confidence_interval":{"confidence_level":0.95,"lower_bound":91513.35181106131,"upper_bound":91864.52855498262},"point_estimate":91689.67593159107,"standard_error":89.17677949133159},"median":{"confidence_interval":{"confidence_level":0.95,"lower_bound":91490.91417399806,"upper_bound":91867.22558139535},"point_estimate":91698.02264264264,"standard_error":100.23178609550607},"median_abs_dev":{"confidence_interval":{"confidence_level":0.95,"lower_bound":482.60310725017644,"upper_bound":838.5690832006643},"point_estimate":595.15797142301,"standard_error":91.28287598393159},"slope":{"confidence_interval":{"confidence_level":0.95,"lower_bound":91707.54349151168,"upper_bound":91997.54895756893},"point_estimate":91846.66023466825,"standard_error":73.9873018948882},"std_dev":{"confidence_interval":{"confidence_level":0.95,"lower_bound":737.430124864179,"upper_bound":1042.0355613481483},"point_estimate":898.4108976238402,"standard_error":77.5641414679819}}