{"mean":{"confidence_interval":{"confidence_level":0.95,"lower_bound":80008.7054060857,"upper_bound":80409.29148264637},"point_estimate":80184.00584601107,"standard_error":103.04069029159021},"median":{"confidence_interval":{"confidence_level":0.95,"lower_bound":80009.2968368344,"upper_bound":80119.94410801964},"point_estimate":80066.044,"standard_error":27.60707612336249},"median_abs_dev":{"confidence_interval":{"confidence_level":0.95,"lower_bound":218.74824166105677,"upper_bound":399.26883547699083},"point_estimate":298.4512714546736,"standard_error":42.14728282447949},"slope":{"confidence_interval":{"confidence_level":0.95,"lower_bound":80144.02034470243,"upper_bound":80649.16371199985},"point_estimate":80346.53433190483,"standard_error":132.40930568169716},"std_dev":{"confidence_interval":{"confidence_level":0.95,"lower_bound":445.3573398709768,"upper_bound":1559.461171546888},"point_estimate":1030.9458849814398,"standard_error":302.4231292372602}}