{"mean":{"confidence_interval":{"confidence_level":0.95,"lower_bound":7245.863837249855,"upper_bound":7289.699947718984},"point_estimate":7264.57622099896,"standard_error":11.27234509848823},"median":{"confidence_interval":{"confidence_level":0.95,"lower_bound":7243.938271604939,"upper_bound":7271.602693602694},"point_estimate":7254.522527100271,"standard_error":5.33805039575979},"median_abs_dev":{"confidence_interval":{"confidence_level":0.95,"lower_bound":39.98098198508658,"upper_bound":74.03037753032739},"point_estimate":54.873790494558904,"standard_error":8.69264558924746},"slope":{"confidence_interval":{"confidence_level":0.95,"lower_bound":7256.643381627255,"upper_bound":7280.295937184674},"point_estimate":7268.664485000739,"standard_error":6.037490588563955},"std_dev":{"confidence_interval":{"confidence_level":0.95,"lower_bound":53.7718756501456,"upper_bound":176.61544372071003},"point_estimate":113.23016495873959,"standard_error":39.14621661784951}}