{"mean":{"confidence_interval":{"confidence_level":0.95,"lower_bound":6963.385765942097,"upper_bound":6981.568905648459},"point_estimate":6972.400610365722,"standard_error":4.642901911672681},"median":{"confidence_interval":{"confidence_level":0.95,"lower_bound":6955.787878787879,"upper_bound":6979.6030465949825},"point_estimate":6969.597816901409,"standard_error":6.791914089849779},"median_abs_dev":{"confidence_interval":{"confidence_level":0.95,"lower_bound":34.805398245717235,"upper_bound":56.668815178755345},"point_estimate":46.83876907506683,"standard_error":5.487276231925871},"slope":{"confidence_interval":{"confidence_level":0.95,"lower_bound":6971.2313952616805,"upper_bound":6987.606162344442},"point_estimate":6979.399535490863,"standard_error":4.178519879833571},"std_dev":{"confidence_interval":{"confidence_level":0.95,"lower_bound":39.77690557489651,"upper_bound":52.8301725117093},"point_estimate":46.551640081908126,"standard_error":3.3373229331946495}}