{"mean":{"confidence_interval":{"confidence_level":0.95,"lower_bound":5231731.998975,"upper_bound":5247474.847699998},"point_estimate":5238827.81,"standard_error":4030.844472600145},"median":{"confidence_interval":{"confidence_level":0.95,"lower_bound":5225365.8,"upper_bound":5233433.05},"point_estimate":5229751.7,"standard_error":2225.466110603207},"median_abs_dev":{"confidence_interval":{"confidence_level":0.95,"lower_bound":14417.024534046512,"upper_bound":23687.870429456234},"point_estimate":19758.46158921774,"standard_error":2386.7638310324683},"slope":null,"std_dev":{"confidence_interval":{"confidence_level":0.95,"lower_bound":22261.050025764365,"upper_bound":58524.69938477704},"point_estimate":40426.77285792373,"standard_error":9761.62646759793}}