{"mean":{"confidence_interval":{"confidence_level":0.95,"lower_bound":5270336.791474998,"upper_bound":5279068.318874999},"point_estimate":5274595.583999999,"standard_error":2229.807906242589},"median":{"confidence_interval":{"confidence_level":0.95,"lower_bound":5265225.85,"upper_bound":5274200.65},"point_estimate":5270270.65,"standard_error":2450.2648597888056},"median_abs_dev":{"confidence_interval":{"confidence_level":0.95,"lower_bound":13321.086633503714,"upper_bound":23986.243674160432},"point_estimate":18816.862345933638,"standard_error":2666.4982699428488},"slope":null,"std_dev":{"confidence_interval":{"confidence_level":0.95,"lower_bound":18491.10856630349,"upper_bound":26054.93129096143},"point_estimate":22452.850629383316,"standard_error":1935.596819342278}}