{"mean":{"confidence_interval":{"confidence_level":0.95,"lower_bound":311790.6862184752,"upper_bound":313550.6103771266},"point_estimate":312612.3886648627,"standard_error":446.3968166936753},"median":{"confidence_interval":{"confidence_level":0.95,"lower_bound":310738.4161624892,"upper_bound":310885.10454545455},"point_estimate":310780.8839285714,"standard_error":39.197173185017704},"median_abs_dev":{"confidence_interval":{"confidence_level":0.95,"lower_bound":220.62779377498182,"upper_bound":463.9205075213609},"point_estimate":276.5181325908095,"standard_error":68.6624031375446},"slope":{"confidence_interval":{"confidence_level":0.95,"lower_bound":312259.1248680168,"upper_bound":314609.4007399433},"point_estimate":313341.24292153097,"standard_error":601.1355769283439},"std_dev":{"confidence_interval":{"confidence_level":0.95,"lower_bound":2949.5614798264246,"upper_bound":5771.123107260665},"point_estimate":4499.643482790755,"standard_error":717.8576199420502}}