{"mean":{"confidence_interval":{"confidence_level":0.95,"lower_bound":311594.724587559,"upper_bound":314064.6819420838},"point_estimate":312695.4740466026,"standard_error":635.6672319047595},"median":{"confidence_interval":{"confidence_level":0.95,"lower_bound":310751.9625,"upper_bound":310840.5169491525},"point_estimate":310788.1663461538,"standard_error":22.31969704270791},"median_abs_dev":{"confidence_interval":{"confidence_level":0.95,"lower_bound":182.5067801537473,"upper_bound":335.90773403646574},"point_estimate":242.86806036706062,"standard_error":38.661405761844925},"slope":{"confidence_interval":{"confidence_level":0.95,"lower_bound":312170.18168343615,"upper_bound":316132.480558827},"point_estimate":313965.0061888577,"standard_error":1017.7286281624475},"std_dev":{"confidence_interval":{"confidence_level":0.95,"lower_bound":3031.9499815204817,"upper_bound":9446.102629626836},"point_estimate":6426.3161448629235,"standard_error":1698.8118901069288}}