{"mean":{"confidence_interval":{"confidence_level":0.95,"lower_bound":81368.3761244032,"upper_bound":81874.11136084056},"point_estimate":81619.49110114713,"standard_error":129.3306955055352},"median":{"confidence_interval":{"confidence_level":0.95,"lower_bound":80763.60530191458,"upper_bound":82577.85238095238},"point_estimate":80843.52420466059,"standard_error":683.3164670468436},"median_abs_dev":{"confidence_interval":{"confidence_level":0.95,"lower_bound":972.3117290538096,"upper_bound":1974.8156387135957},"point_estimate":1420.5833483016925,"standard_error":286.0731654910514},"slope":{"confidence_interval":{"confidence_level":0.95,"lower_bound":80710.13189874047,"upper_bound":81021.50424841905},"point_estimate":80852.04860731702,"standard_error":79.40833603410083},"std_dev":{"confidence_interval":{"confidence_level":0.95,"lower_bound":1213.5356570270394,"upper_bound":1360.9868796320131},"point_estimate":1295.4053856037401,"standard_error":37.59877298451152}}