{"mean":{"confidence_interval":{"confidence_level":0.95,"lower_bound":82031.33837200982,"upper_bound":82198.11829814002},"point_estimate":82108.5940657809,"standard_error":42.597426408266976},"median":{"confidence_interval":{"confidence_level":0.95,"lower_bound":81992.27565236621,"upper_bound":82076.88961038961},"point_estimate":82032.71908315565,"standard_error":20.36478394265293},"median_abs_dev":{"confidence_interval":{"confidence_level":0.95,"lower_bound":129.83383347567425,"upper_bound":246.87714464332097},"point_estimate":184.32296493366155,"standard_error":30.132280951367253},"slope":{"confidence_interval":{"confidence_level":0.95,"lower_bound":82083.277938512,"upper_bound":82309.69533133265},"point_estimate":82189.77871477127,"standard_error":57.969696028817694},"std_dev":{"confidence_interval":{"confidence_level":0.95,"lower_bound":254.16909739099344,"upper_bound":609.4558052096327},"point_estimate":427.82155305614515,"standard_error":96.14375056081872}}