{"mean":{"confidence_interval":{"confidence_level":0.95,"lower_bound":59165.78173810703,"upper_bound":59824.046331627396},"point_estimate":59539.47729723362,"standard_error":169.75824849154483},"median":{"confidence_interval":{"confidence_level":0.95,"lower_bound":59649.103758169935,"upper_bound":59841.87777689095},"point_estimate":59733.11979913917,"standard_error":55.63154938761589},"median_abs_dev":{"confidence_interval":{"confidence_level":0.95,"lower_bound":322.29128751372104,"upper_bound":654.5975474402517},"point_estimate":495.17341276558693,"standard_error":88.16995681921603},"slope":{"confidence_interval":{"confidence_level":0.95,"lower_bound":59980.52197691862,"upper_bound":60305.81792415227},"point_estimate":60139.35096028303,"standard_error":83.05921539662623},"std_dev":{"confidence_interval":{"confidence_level":0.95,"lower_bound":723.9788174766171,"upper_bound":2658.6030115137164},"point_estimate":1717.315314408438,"standard_error":558.6920148186969}}