{"mean":{"confidence_interval":{"confidence_level":0.95,"lower_bound":6678043.964000001,"upper_bound":6683637.255437501},"point_estimate":6680685.71625,"standard_error":1434.1693543130916},"median":{"confidence_interval":{"confidence_level":0.95,"lower_bound":6675510.3125,"upper_bound":6679051.375},"point_estimate":6677018.125,"standard_error":941.034109939111},"median_abs_dev":{"confidence_interval":{"confidence_level":0.95,"lower_bound":5710.467771431435,"upper_bound":10018.854647129774},"point_estimate":8134.192093089223,"standard_error":1095.712831807705},"slope":null,"std_dev":{"confidence_interval":{"confidence_level":0.95,"lower_bound":9979.85563902332,"upper_bound":18031.402265211593},"point_estimate":14410.207070214388,"standard_error":2052.989928757352}}