{"mean":{"confidence_interval":{"confidence_level":0.95,"lower_bound":69369.35579591065,"upper_bound":70727.8299387827},"point_estimate":70070.64763072628,"standard_error":346.73407019914896},"median":{"confidence_interval":{"confidence_level":0.95,"lower_bound":69218.68530778165,"upper_bound":69383.2441025641},"point_estimate":69280.00478927203,"standard_error":38.20549940619879},"median_abs_dev":{"confidence_interval":{"confidence_level":0.95,"lower_bound":353.6455694022994,"upper_bound":886.3514282035214},"point_estimate":566.4704265178508,"standard_error":141.87434877390936},"slope":{"confidence_interval":{"confidence_level":0.95,"lower_bound":70075.98313112253,"upper_bound":71353.53006017422},"point_estimate":70681.70739845328,"standard_error":326.5770179172231},"std_dev":{"confidence_interval":{"confidence_level":0.95,"lower_bound":2445.8373688383367,"upper_bound":4586.931103620444},"point_estimate":3486.105815475509,"standard_error":564.1502631810507}}