{"mean":{"confidence_interval":{"confidence_level":0.95,"lower_bound":65369.44988020263,"upper_bound":66743.35215509411},"point_estimate":66107.66092273848,"standard_error":350.03465437441923},"median":{"confidence_interval":{"confidence_level":0.95,"lower_bound":65827.1037037037,"upper_bound":66146.54187156839},"point_estimate":65989.35564580347,"standard_error":78.8175547414955},"median_abs_dev":{"confidence_interval":{"confidence_level":0.95,"lower_bound":415.23162869568677,"upper_bound":888.5561856761902},"point_estimate":551.4880940370437,"standard_error":122.06600396503413},"slope":{"confidence_interval":{"confidence_level":0.95,"lower_bound":66350.12111327844,"upper_bound":67008.6895018481},"point_estimate":66651.82887089306,"standard_error":168.70257718882615},"std_dev":{"confidence_interval":{"confidence_level":0.95,"lower_bound":2100.47420251022,"upper_bound":4987.5344926341795},"point_estimate":3501.297009212089,"standard_error":787.4881975400097}}