{"mean":{"confidence_interval":{"confidence_level":0.95,"lower_bound":74105.39113082127,"upper_bound":74577.04003171016},"point_estimate":74333.25639360098,"standard_error":120.48637141259408},"median":{"confidence_interval":{"confidence_level":0.95,"lower_bound":73545.3376344086,"upper_bound":73981.07666666666},"point_estimate":73748.8607219007,"standard_error":122.0209465709844},"median_abs_dev":{"confidence_interval":{"confidence_level":0.95,"lower_bound":408.0336819536946,"upper_bound":1035.1347152877875},"point_estimate":661.9260002092517,"standard_error":179.97052483854338},"slope":{"confidence_interval":{"confidence_level":0.95,"lower_bound":73560.6075070928,"upper_bound":73709.89164439678},"point_estimate":73627.66707728684,"standard_error":38.105275018708454},"std_dev":{"confidence_interval":{"confidence_level":0.95,"lower_bound":1019.2678432801164,"upper_bound":1421.785351506686},"point_estimate":1214.7753023298355,"standard_error":104.32489056234066}}