{"mean":{"confidence_interval":{"confidence_level":0.95,"lower_bound":69587337.27,"upper_bound":70079093.76},"point_estimate":69796380.82,"standard_error":125876.38222054197},"median":{"confidence_interval":{"confidence_level":0.95,"lower_bound":69519255.5,"upper_bound":69809060.0},"point_estimate":69674274.5,"standard_error":76309.55713283455},"median_abs_dev":{"confidence_interval":{"confidence_level":0.95,"lower_bound":475890.86995124817,"upper_bound":926996.3748425245},"point_estimate":722900.1798659563,"standard_error":112011.75937652521},"slope":null,"std_dev":{"confidence_interval":{"confidence_level":0.95,"lower_bound":615215.0782408064,"upper_bound":1960732.4745327644},"point_estimate":1265049.109207502,"standard_error":428797.4868552736}}