{"mean":{"confidence_interval":{"confidence_level":0.95,"lower_bound":70516137.88125,"upper_bound":70808290.44675},"point_estimate":70651371.34,"standard_error":74724.50725704446},"median":{"confidence_interval":{"confidence_level":0.95,"lower_bound":70389905.0,"upper_bound":70621022.0},"point_estimate":70530287.0,"standard_error":53792.077334834554},"median_abs_dev":{"confidence_interval":{"confidence_level":0.95,"lower_bound":335746.6248393059,"upper_bound":539428.4331232309},"point_estimate":412717.2850728035,"standard_error":51824.91194930446},"slope":null,"std_dev":{"confidence_interval":{"confidence_level":0.95,"lower_bound":487197.081652544,"upper_bound":1005762.3830461609},"point_estimate":747717.5789531635,"standard_error":136440.40375533391}}