{"mean":{"confidence_interval":{"confidence_level":0.95,"lower_bound":6588722.043937501,"upper_bound":6632814.3069687495},"point_estimate":6609425.3925,"standard_error":11281.776635778526},"median":{"confidence_interval":{"confidence_level":0.95,"lower_bound":6558895.8125,"upper_bound":6566274.125},"point_estimate":6560533.375,"standard_error":1872.2965619745103},"median_abs_dev":{"confidence_interval":{"confidence_level":0.95,"lower_bound":6781.87559209764,"upper_bound":16934.349561855197},"point_estimate":9626.150979101658,"standard_error":2569.190260629941},"slope":null,"std_dev":{"confidence_interval":{"confidence_level":0.95,"lower_bound":79414.69949326651,"upper_bound":141678.3890486372},"point_estimate":113724.62047379672,"standard_error":15933.886719738166}}