{"mean":{"confidence_interval":{"confidence_level":0.95,"lower_bound":6556636.11103125,"upper_bound":6567994.7759375},"point_estimate":6561366.37,"standard_error":2964.6964917161235},"median":{"confidence_interval":{"confidence_level":0.95,"lower_bound":6554503.375,"upper_bound":6556746.375},"point_estimate":6555211.0,"standard_error":590.7893065282849},"median_abs_dev":{"confidence_interval":{"confidence_level":0.95,"lower_bound":3590.949798747897,"upper_bound":6016.205368191004},"point_estimate":4863.113238662481,"standard_error":602.3767259140731},"slope":null,"std_dev":{"confidence_interval":{"confidence_level":0.95,"lower_bound":6893.7991785944905,"upper_bound":47045.950614402005},"point_estimate":29795.905855650926,"standard_error":10920.041703669745}}