{"mean":{"confidence_interval":{"confidence_level":0.95,"lower_bound":50173.05552715736,"upper_bound":50604.49892918318},"point_estimate":50421.062037132186,"standard_error":111.21971254519873},"median":{"confidence_interval":{"confidence_level":0.95,"lower_bound":50485.6125,"upper_bound":50580.239655172416},"point_estimate":50541.435583548664,"standard_error":25.02957247696502},"median_abs_dev":{"confidence_interval":{"confidence_level":0.95,"lower_bound":205.28253279898712,"upper_bound":335.1940201485134},"point_estimate":268.57355832397866,"standard_error":33.33759336760784},"slope":{"confidence_interval":{"confidence_level":0.95,"lower_bound":50547.19703243805,"upper_bound":50784.23035270984},"point_estimate":50652.22006901138,"standard_error":60.96381997667717},"std_dev":{"confidence_interval":{"confidence_level":0.95,"lower_bound":412.54789115932044,"upper_bound":1762.6902186033456},"point_estimate":1119.0568065425812,"standard_error":388.25087802874924}}