{"mean":{"confidence_interval":{"confidence_level":0.95,"lower_bound":15572.55429758128,"upper_bound":15647.283372128268},"point_estimate":15607.995337599914,"standard_error":19.069710215781605},"median":{"confidence_interval":{"confidence_level":0.95,"lower_bound":15518.821109693878,"upper_bound":15604.75625},"point_estimate":15569.930950342467,"standard_error":22.782351985227336},"median_abs_dev":{"confidence_interval":{"confidence_level":0.95,"lower_bound":96.8359266743001,"upper_bound":166.96874579956716},"point_estimate":138.3530525437422,"standard_error":19.72318487541254},"slope":{"confidence_interval":{"confidence_level":0.95,"lower_bound":15647.799285070303,"upper_bound":15712.477348248092},"point_estimate":15680.001869643122,"standard_error":16.501160201090034},"std_dev":{"confidence_interval":{"confidence_level":0.95,"lower_bound":134.6992764910622,"upper_bound":245.52147623820915},"point_estimate":192.18392691089625,"standard_error":28.420353745315634}}