{"mean":{"confidence_interval":{"confidence_level":0.95,"lower_bound":6524879.08290625,"upper_bound":6527980.65565625},"point_estimate":6526274.69125,"standard_error":795.5007311906201},"median":{"confidence_interval":{"confidence_level":0.95,"lower_bound":6523747.5625,"upper_bound":6525114.25},"point_estimate":6524373.125,"standard_error":370.78419208584967},"median_abs_dev":{"confidence_interval":{"confidence_level":0.95,"lower_bound":2616.5109660476446,"upper_bound":4757.755978032947},"point_estimate":3438.3346639573574,"standard_error":544.4870425909444},"slope":null,"std_dev":{"confidence_interval":{"confidence_level":0.95,"lower_bound":4238.624452956988,"upper_bound":11636.291464316142},"point_estimate":7986.102696014658,"standard_error":1983.926049451159}}