{"mean":{"confidence_interval":{"confidence_level":0.95,"lower_bound":6525686.555,"upper_bound":6534041.71346875},"point_estimate":6529207.76875,"standard_error":2163.1734892007075},"median":{"confidence_interval":{"confidence_level":0.95,"lower_bound":6524198.0,"upper_bound":6526219.25},"point_estimate":6524953.5625,"standard_error":628.7346536336715},"median_abs_dev":{"confidence_interval":{"confidence_level":0.95,"lower_bound":2645.8849780261517,"upper_bound":4588.832243531942},"point_estimate":3378.4746900200844,"standard_error":485.27851289228687},"slope":null,"std_dev":{"confidence_interval":{"confidence_level":0.95,"lower_bound":4188.493895952003,"upper_bound":33184.698647451536},"point_estimate":21781.567491464408,"standard_error":7560.103588181422}}