{"mean":{"confidence_interval":{"confidence_level":0.95,"lower_bound":74850054.44,"upper_bound":76889097.27},"point_estimate":75841306.88,"standard_error":520479.8446856628},"median":{"confidence_interval":{"confidence_level":0.95,"lower_bound":73320778.0,"upper_bound":75409643.5},"point_estimate":74732387.0,"standard_error":652970.5018308434},"median_abs_dev":{"confidence_interval":{"confidence_level":0.95,"lower_bound":2633118.3096528053,"upper_bound":5055521.356746554},"point_estimate":4362766.882145405,"standard_error":660739.4509264027},"slope":null,"std_dev":{"confidence_interval":{"confidence_level":0.95,"lower_bound":4261131.644272592,"upper_bound":6132608.487382662},"point_estimate":5245223.738179349,"standard_error":477662.7694840293}}