{"mean":{"confidence_interval":{"confidence_level":0.95,"lower_bound":69617.2157994671,"upper_bound":70440.2458812041},"point_estimate":70021.1972385754,"standard_error":209.80107300304448},"median":{"confidence_interval":{"confidence_level":0.95,"lower_bound":69493.89743589744,"upper_bound":70665.46464646465},"point_estimate":70103.6868458922,"standard_error":258.1783598017379},"median_abs_dev":{"confidence_interval":{"confidence_level":0.95,"lower_bound":1657.810598615401,"upper_bound":2630.4657244614887},"point_estimate":2286.652597695654,"standard_error":246.00940167387614},"slope":{"confidence_interval":{"confidence_level":0.95,"lower_bound":69352.50825858772,"upper_bound":70342.53182661894},"point_estimate":69828.76293236787,"standard_error":252.58539326728175},"std_dev":{"confidence_interval":{"confidence_level":0.95,"lower_bound":1760.2970080774815,"upper_bound":2450.6617846797644},"point_estimate":2110.714630054368,"standard_error":177.16391316611396}}