{"mean":{"confidence_interval":{"confidence_level":0.95,"lower_bound":6582405.5975,"upper_bound":6630000.04},"point_estimate":6604432.39875,"standard_error":12169.374143461317},"median":{"confidence_interval":{"confidence_level":0.95,"lower_bound":6556941.875,"upper_bound":6561322.125},"point_estimate":6558141.375,"standard_error":1025.624466738067},"median_abs_dev":{"confidence_interval":{"confidence_level":0.95,"lower_bound":5475.519690290093,"upper_bound":11922.605675831437},"point_estimate":7567.004940658808,"standard_error":1644.3039628417268},"slope":null,"std_dev":{"confidence_interval":{"confidence_level":0.95,"lower_bound":79271.32100064111,"upper_bound":157477.2896496005},"point_estimate":122659.7400577686,"standard_error":19924.983212881667}}