{"mean":{"confidence_interval":{"confidence_level":0.95,"lower_bound":373481.96385125746,"upper_bound":374690.4237754666},"point_estimate":373970.37369686284,"standard_error":317.609420684837},"median":{"confidence_interval":{"confidence_level":0.95,"lower_bound":373237.30049435026,"upper_bound":373782.0683760684},"point_estimate":373434.501606128,"standard_error":120.41268187514625},"median_abs_dev":{"confidence_interval":{"confidence_level":0.95,"lower_bound":700.0919718608363,"upper_bound":1159.0261105826314},"point_estimate":894.6910527106139,"standard_error":114.13302499465836},"slope":{"confidence_interval":{"confidence_level":0.95,"lower_bound":373448.3551095905,"upper_bound":373976.3984820024},"point_estimate":373676.28643909167,"standard_error":134.81004195414116},"std_dev":{"confidence_interval":{"confidence_level":0.95,"lower_bound":1058.8016722614245,"upper_bound":5213.142717733082},"point_estimate":3203.666082845961,"standard_error":1339.267920490809}}