{"mean":{"confidence_interval":{"confidence_level":0.95,"lower_bound":592365.8144302462,"upper_bound":593369.103641746},"point_estimate":592785.9725837642,"standard_error":259.1611494934769},"median":{"confidence_interval":{"confidence_level":0.95,"lower_bound":592239.7954545454,"upper_bound":592720.2462500001},"point_estimate":592496.7287087912,"standard_error":125.89144966720899},"median_abs_dev":{"confidence_interval":{"confidence_level":0.95,"lower_bound":896.1570288309193,"upper_bound":1361.936302959756},"point_estimate":1161.1856011965992,"standard_error":119.04627101894715},"slope":{"confidence_interval":{"confidence_level":0.95,"lower_bound":592525.9248283746,"upper_bound":594702.7550944956},"point_estimate":593306.1102940742,"standard_error":613.174689968949},"std_dev":{"confidence_interval":{"confidence_level":0.95,"lower_bound":1029.580280117323,"upper_bound":4127.6955863355415},"point_estimate":2607.9826731886446,"standard_error":938.8386179535484}}