{"mean":{"confidence_interval":{"confidence_level":0.95,"lower_bound":55756.37914268615,"upper_bound":56143.057453384106},"point_estimate":55925.211762663435,"standard_error":99.3454496432253},"median":{"confidence_interval":{"confidence_level":0.95,"lower_bound":55753.910416666666,"upper_bound":55969.689598997495},"point_estimate":55867.72242184141,"standard_error":66.62197776363229},"median_abs_dev":{"confidence_interval":{"confidence_level":0.95,"lower_bound":280.42193830788653,"upper_bound":486.46551928314733},"point_estimate":366.5303513670828,"standard_error":54.09977574285913},"slope":{"confidence_interval":{"confidence_level":0.95,"lower_bound":55923.67631309689,"upper_bound":56460.60037806735},"point_estimate":56131.21923107236,"standard_error":142.58643263447468},"std_dev":{"confidence_interval":{"confidence_level":0.95,"lower_bound":467.3189814247159,"upper_bound":1511.8152129343653},"point_estimate":997.5135026539532,"standard_error":298.0108643331787}}