{"mean":{"confidence_interval":{"confidence_level":0.95,"lower_bound":311264.3643089521,"upper_bound":314180.27389761683},"point_estimate":312533.78588135034,"standard_error":751.8227015063826},"median":{"confidence_interval":{"confidence_level":0.95,"lower_bound":310704.77127659577,"upper_bound":310795.1875},"point_estimate":310732.12938596494,"standard_error":21.585527802621797},"median_abs_dev":{"confidence_interval":{"confidence_level":0.95,"lower_bound":135.97375503296777,"upper_bound":259.44080028755377},"point_estimate":197.60220515798378,"standard_error":30.693358659276445},"slope":{"confidence_interval":{"confidence_level":0.95,"lower_bound":311582.8730762231,"upper_bound":316572.0085037405},"point_estimate":313637.0871361017,"standard_error":1310.3372290548648},"std_dev":{"confidence_interval":{"confidence_level":0.95,"lower_bound":2576.6192365719435,"upper_bound":11312.412547084614},"point_estimate":7567.839513162415,"standard_error":2245.340953974411}}