{"mean":{"confidence_interval":{"confidence_level":0.95,"lower_bound":351583.0072866272,"upper_bound":353071.3818402229},"point_estimate":352114.4714756137,"standard_error":437.2555950922015},"median":{"confidence_interval":{"confidence_level":0.95,"lower_bound":351457.46553586866,"upper_bound":351573.49333333335},"point_estimate":351511.9920883324,"standard_error":26.693324154862783},"median_abs_dev":{"confidence_interval":{"confidence_level":0.95,"lower_bound":175.8267338492204,"upper_bound":338.26508060172426},"point_estimate":271.53182831666294,"standard_error":42.33400988066704},"slope":{"confidence_interval":{"confidence_level":0.95,"lower_bound":351582.0918302995,"upper_bound":354386.6188665052},"point_estimate":352519.4165154426,"standard_error":805.6144084863562},"std_dev":{"confidence_interval":{"confidence_level":0.95,"lower_bound":466.9935083674962,"upper_bound":7552.930988044723},"point_estimate":4434.613722406706,"standard_error":2470.162314779579}}