{"mean":{"confidence_interval":{"confidence_level":0.95,"lower_bound":5888.480763373191,"upper_bound":5898.594497766883},"point_estimate":5893.394409106762,"standard_error":2.585503107462555},"median":{"confidence_interval":{"confidence_level":0.95,"lower_bound":5883.793313069908,"upper_bound":5892.050324675325},"point_estimate":5887.925170068027,"standard_error":1.8985714833518552},"median_abs_dev":{"confidence_interval":{"confidence_level":0.95,"lower_bound":13.9501147943534,"upper_bound":27.145643266762413},"point_estimate":20.501914504438968,"standard_error":3.4032627279586483},"slope":{"confidence_interval":{"confidence_level":0.95,"lower_bound":5885.206373234696,"upper_bound":5894.018558220304},"point_estimate":5889.4642584812855,"standard_error":2.251500434137521},"std_dev":{"confidence_interval":{"confidence_level":0.95,"lower_bound":20.385002059894916,"upper_bound":31.315255517976464},"point_estimate":25.94810534628312,"standard_error":2.804797509153336}}