{"mean":{"confidence_interval":{"confidence_level":0.95,"lower_bound":4013.881693042004,"upper_bound":4037.141469444607},"point_estimate":4025.5504106107132,"standard_error":5.938966545417057},"median":{"confidence_interval":{"confidence_level":0.95,"lower_bound":4008.5679653679654,"upper_bound":4048.813295535081},"point_estimate":4034.722961513373,"standard_error":10.003777432132514},"median_abs_dev":{"confidence_interval":{"confidence_level":0.95,"lower_bound":50.17800781839279,"upper_bound":77.53709213239888},"point_estimate":63.911442665946026,"standard_error":7.050016923965376},"slope":{"confidence_interval":{"confidence_level":0.95,"lower_bound":4039.5259241688495,"upper_bound":4057.7931073223594},"point_estimate":4048.8451682183145,"standard_error":4.64367022952648},"std_dev":{"confidence_interval":{"confidence_level":0.95,"lower_bound":51.64807260272151,"upper_bound":66.30768474644258},"point_estimate":59.43702036421823,"standard_error":3.7612677497789586}}