{"mean":{"confidence_interval":{"confidence_level":0.95,"lower_bound":25085854.188624997,"upper_bound":25266833.173},"point_estimate":25177517.1,"standard_error":45930.21607604514},"median":{"confidence_interval":{"confidence_level":0.95,"lower_bound":25088252.75,"upper_bound":25330725.75},"point_estimate":25189002.25,"standard_error":65115.432549309546},"median_abs_dev":{"confidence_interval":{"confidence_level":0.95,"lower_bound":352319.49799507856,"upper_bound":557555.8123514056},"point_estimate":453364.9872511625,"standard_error":52481.65611196265},"slope":null,"std_dev":{"confidence_interval":{"confidence_level":0.95,"lower_bound":390245.48784108215,"upper_bound":523803.67432935117},"point_estimate":461276.3712574703,"standard_error":34163.7689371237}}