{"mean":{"confidence_interval":{"confidence_level":0.95,"lower_bound":79996.54935026605,"upper_bound":80148.24245182658},"point_estimate":80071.06250662901,"standard_error":38.62965317232421},"median":{"confidence_interval":{"confidence_level":0.95,"lower_bound":80023.47093023256,"upper_bound":80143.832890625},"point_estimate":80088.29493065967,"standard_error":35.27217794197422},"median_abs_dev":{"confidence_interval":{"confidence_level":0.95,"lower_bound":177.51269043435676,"upper_bound":305.13391458880324},"point_estimate":232.9900981662333,"standard_error":32.24277069345047},"slope":{"confidence_interval":{"confidence_level":0.95,"lower_bound":80117.93095616193,"upper_bound":80271.15539013119},"point_estimate":80188.6749852224,"standard_error":39.410177330607446},"std_dev":{"confidence_interval":{"confidence_level":0.95,"lower_bound":289.8889110458261,"upper_bound":485.8093403118476},"point_estimate":388.9383487598051,"standard_error":50.387291831688266}}