{"mean":{"confidence_interval":{"confidence_level":0.95,"lower_bound":55183608.849750005,"upper_bound":55438055.47},"point_estimate":55314824.58,"standard_error":64674.57166526049},"median":{"confidence_interval":{"confidence_level":0.95,"lower_bound":55423662.5,"upper_bound":55645897.5},"point_estimate":55522887.5,"standard_error":49862.05917041952},"median_abs_dev":{"confidence_interval":{"confidence_level":0.95,"lower_bound":278745.1036512852,"upper_bound":590821.2786108255},"point_estimate":407096.0072726011,"standard_error":84117.33828962772},"slope":null,"std_dev":{"confidence_interval":{"confidence_level":0.95,"lower_bound":528150.2108957554,"upper_bound":753426.7258571556},"point_estimate":650492.4055148287,"standard_error":57530.600471320584}}