{"mean":{"confidence_interval":{"confidence_level":0.95,"lower_bound":57762747.95,"upper_bound":58018243.42075},"point_estimate":57888982.82,"standard_error":64924.7568265111},"median":{"confidence_interval":{"confidence_level":0.95,"lower_bound":57726110.0,"upper_bound":58019436.0},"point_estimate":57853707.0,"standard_error":66519.62069432462},"median_abs_dev":{"confidence_interval":{"confidence_level":0.95,"lower_bound":502772.6313740015,"upper_bound":763446.3239461184},"point_estimate":653342.5195008516,"standard_error":66535.31052505196},"slope":null,"std_dev":{"confidence_interval":{"confidence_level":0.95,"lower_bound":544392.9638927135,"upper_bound":767739.8071581369},"point_estimate":654956.3449901344,"standard_error":57576.26324777398}}