{"mean":{"confidence_interval":{"confidence_level":0.95,"lower_bound":991024.3572829973,"upper_bound":996729.9620349456},"point_estimate":993602.9744842879,"standard_error":1464.3000865331085},"median":{"confidence_interval":{"confidence_level":0.95,"lower_bound":988475.2307692308,"upper_bound":989950.2558139535},"point_estimate":989134.9355179704,"standard_error":381.7135795784749},"median_abs_dev":{"confidence_interval":{"confidence_level":0.95,"lower_bound":2282.4626594781876,"upper_bound":4273.633510855117},"point_estimate":3082.5264631872287,"standard_error":480.4475742590762},"slope":{"confidence_interval":{"confidence_level":0.95,"lower_bound":990378.1552721469,"upper_bound":994617.3373581897},"point_estimate":992310.7702083641,"standard_error":1087.652212662083},"std_dev":{"confidence_interval":{"confidence_level":0.95,"lower_bound":7850.952570176631,"upper_bound":20186.626510540384},"point_estimate":14663.905423573877,"standard_error":3141.619361698017}}