{"mean":{"confidence_interval":{"confidence_level":0.95,"lower_bound":27925915.794875,"upper_bound":28992235.879249997},"point_estimate":28443939.575,"standard_error":271690.52622297587},"median":{"confidence_interval":{"confidence_level":0.95,"lower_bound":27276234.75,"upper_bound":28708065.5},"point_estimate":28156757.25,"standard_error":357977.35972134955},"median_abs_dev":{"confidence_interval":{"confidence_level":0.95,"lower_bound":2297048.4780192375,"upper_bound":3744183.4279162027},"point_estimate":3174226.528546214,"standard_error":372384.4909099423},"slope":null,"std_dev":{"confidence_interval":{"confidence_level":0.95,"lower_bound":2271369.4191846214,"upper_bound":3138466.50134869},"point_estimate":2725312.515054191,"standard_error":221283.71289038938}}