{"mean":{"confidence_interval":{"confidence_level":0.95,"lower_bound":46366767.935,"upper_bound":46430843.035375},"point_estimate":46395545.34,"standard_error":16458.58957725554},"median":{"confidence_interval":{"confidence_level":0.95,"lower_bound":46340139.5,"upper_bound":46357943.5},"point_estimate":46346695.25,"standard_error":4436.678746976813},"median_abs_dev":{"confidence_interval":{"confidence_level":0.95,"lower_bound":26578.477065637715,"upper_bound":48217.48699396849},"point_estimate":35800.341564416885,"standard_error":5405.1083315829865},"slope":null,"std_dev":{"confidence_interval":{"confidence_level":0.95,"lower_bound":75485.92257489315,"upper_bound":231787.80575494692},"point_estimate":164565.2643681527,"standard_error":39312.289366776866}}