{"mean":{"confidence_interval":{"confidence_level":0.95,"lower_bound":40024927.24587499,"upper_bound":40114048.985874996},"point_estimate":40068928.64,"standard_error":22771.590245871408},"median":{"confidence_interval":{"confidence_level":0.95,"lower_bound":39944622.5,"upper_bound":40059685.0},"point_estimate":39981015.5,"standard_error":27718.425349559067},"median_abs_dev":{"confidence_interval":{"confidence_level":0.95,"lower_bound":86860.99199540915,"upper_bound":217315.70497937468},"point_estimate":135975.54463595152,"standard_error":35306.529352854515},"slope":null,"std_dev":{"confidence_interval":{"confidence_level":0.95,"lower_bound":187677.55610639902,"upper_bound":264326.61928368086},"point_estimate":227740.7939632257,"standard_error":19474.37634312248}}