{"mean":{"confidence_interval":{"confidence_level":0.95,"lower_bound":6544587.3007499995,"upper_bound":6551175.63984375},"point_estimate":6547786.925,"standard_error":1688.0630343613034},"median":{"confidence_interval":{"confidence_level":0.95,"lower_bound":6541558.375,"upper_bound":6549502.0},"point_estimate":6544019.3125,"standard_error":2528.8221537194},"median_abs_dev":{"confidence_interval":{"confidence_level":0.95,"lower_bound":10434.677608497444,"upper_bound":16399.40895885229},"point_estimate":12581.99201412499,"standard_error":1512.3961098781435},"slope":null,"std_dev":{"confidence_interval":{"confidence_level":0.95,"lower_bound":13564.956279993516,"upper_bound":20033.632766142127},"point_estimate":16964.687379620576,"standard_error":1657.5114244405847}}