{"mean":{"confidence_interval":{"confidence_level":0.95,"lower_bound":6493946.05625,"upper_bound":6523131.55375},"point_estimate":6506320.67,"standard_error":7522.959651194955},"median":{"confidence_interval":{"confidence_level":0.95,"lower_bound":6488818.0,"upper_bound":6492328.5},"point_estimate":6490638.1875,"standard_error":960.4532831805539},"median_abs_dev":{"confidence_interval":{"confidence_level":0.95,"lower_bound":4600.044405832887,"upper_bound":8867.708430066705},"point_estimate":6435.31784825027,"standard_error":1198.8440654656206},"slope":null,"std_dev":{"confidence_interval":{"confidence_level":0.95,"lower_bound":16008.876036805592,"upper_bound":116456.06067905044},"point_estimate":75717.18323498056,"standard_error":25481.6093616281}}