{"mean":{"confidence_interval":{"confidence_level":0.95,"lower_bound":9610.1279703757,"upper_bound":9732.731879556864},"point_estimate":9668.73745419393,"standard_error":31.377730924270434},"median":{"confidence_interval":{"confidence_level":0.95,"lower_bound":9524.561231451475,"upper_bound":9594.856607495069},"point_estimate":9548.745167040317,"standard_error":15.913559584864313},"median_abs_dev":{"confidence_interval":{"confidence_level":0.95,"lower_bound":119.4324540792223,"upper_bound":241.10532398528682},"point_estimate":157.88983587306538,"standard_error":30.546780572381444},"slope":{"confidence_interval":{"confidence_level":0.95,"lower_bound":9502.55034863003,"upper_bound":9651.794693016473},"point_estimate":9558.490525286743,"standard_error":40.61152467987225},"std_dev":{"confidence_interval":{"confidence_level":0.95,"lower_bound":236.14561479124248,"upper_bound":388.7043350003168},"point_estimate":315.7556429988678,"standard_error":39.07520995245694}}