{"mean":{"confidence_interval":{"confidence_level":0.95,"lower_bound":6672.351132004867,"upper_bound":6695.242241179286},"point_estimate":6683.628119766886,"standard_error":5.836259388643371},"median":{"confidence_interval":{"confidence_level":0.95,"lower_bound":6669.502024291498,"upper_bound":6695.014423076923},"point_estimate":6681.198585929707,"standard_error":6.5912735759533705},"median_abs_dev":{"confidence_interval":{"confidence_level":0.95,"lower_bound":34.94509073968888,"upper_bound":56.90885270416101},"point_estimate":45.35493306235805,"standard_error":5.5781414019814815},"slope":{"confidence_interval":{"confidence_level":0.95,"lower_bound":6690.478841099707,"upper_bound":6712.6674615472475},"point_estimate":6701.666805651863,"standard_error":5.6503272214567914},"std_dev":{"confidence_interval":{"confidence_level":0.95,"lower_bound":47.73559632631594,"upper_bound":69.21295036976561},"point_estimate":58.66317903094572,"standard_error":5.5089358052737305}}