{"mean":{"confidence_interval":{"confidence_level":0.95,"lower_bound":6823.914521878153,"upper_bound":6928.512215415513},"point_estimate":6864.122761651109,"standard_error":27.926858985601662},"median":{"confidence_interval":{"confidence_level":0.95,"lower_bound":6821.923076923077,"upper_bound":6842.493396746622},"point_estimate":6830.987611806798,"standard_error":5.140676924956882},"median_abs_dev":{"confidence_interval":{"confidence_level":0.95,"lower_bound":34.052842047467905,"upper_bound":61.044617779489414},"point_estimate":48.0028794618197,"standard_error":7.016259195238808},"slope":{"confidence_interval":{"confidence_level":0.95,"lower_bound":6824.32038179383,"upper_bound":6958.995524184199},"point_estimate":6874.514551158904,"standard_error":36.245562850820946},"std_dev":{"confidence_interval":{"confidence_level":0.95,"lower_bound":51.26065361326635,"upper_bound":468.28466209691254},"point_estimate":281.84723059488795,"standard_error":129.35273325541115}}